pydnsbl/__init__.py
pydnsbl/checker.py
pydnsbl/providers.py
pydnsbl/tests.py
pydnsbl-1.1.6.dist-info/LICENSE
pydnsbl-1.1.6.dist-info/METADATA
pydnsbl-1.1.6.dist-info/WHEEL
pydnsbl-1.1.6.dist-info/top_level.txt
pydnsbl-1.1.6.dist-info/RECORD
