Metadata-Version: 2.1
Name: pydnsbl
Version: 1.1.6
Summary: Async dnsbl lists checker based on asyncio/aiodns.
Home-page: https://github.com/dmippolitov/pydnsbl/
Author: Dmitry ippolitov
Author-email: ippolitov87@gmail.com
License: MIT
Classifier: Environment :: Web Environment
Classifier: Intended Audience :: Developers
Classifier: License :: OSI Approved :: MIT License
Classifier: Operating System :: OS Independent
Classifier: Programming Language :: Python
Classifier: Programming Language :: Python :: 3.5
Classifier: Topic :: Utilities
License-File: LICENSE
Requires-Dist: aiodns <=2.0,>=1.1.1
Requires-Dist: idna <3,>=2.9
